scraperx/__init__.py
scraperx/arguments.py
scraperx/config.py
scraperx/dispatch.py
scraperx/download.py
scraperx/exceptions.py
scraperx/extract.py
scraperx/parsers.py
scraperx/proxies.py
scraperx/run_cli.py
scraperx/save_to.py
scraperx/scraper.py
scraperx/test.py
scraperx/trigger.py
scraperx/user_agent.py
scraperx/utils.py
scraperx/write.py
tests/__init__.py
tests/test_parsers.py
tests/test_utils.py
scraperx-0.7.1.dist-info/LICENSE
scraperx-0.7.1.dist-info/METADATA
scraperx-0.7.1.dist-info/WHEEL
scraperx-0.7.1.dist-info/top_level.txt
scraperx-0.7.1.dist-info/RECORD
