Metadata-Version: 2.1
Name: scraperx
Version: 0.7.1
Summary: ScraperX SDK
Home-page: https://github.com/xtream1101/scraperx
Author: Eddy Hintze
Author-email: eddy@hintze.co
License: MIT
Platform: UNKNOWN
Requires-Python: >=3.6.0
License-File: LICENSE
Requires-Dist: pyyaml
Requires-Dist: parsel
Requires-Dist: requests
Requires-Dist: boto3
Requires-Dist: deepdiff
Requires-Dist: smart-open >=1.8.4
Requires-Dist: charset-normalizer
